{"expireTime":9007200852752605000,"key":"0d586564b52c05a33654af67bc91190c{\"background\":\"rgba(0,0,0,1)\",\"duotone\":false,\"grayscale\":false,\"rotate\":0,\"trim\":false,\"toFormat\":\"webp\",\"toFormatBase64\":\"\",\"cropFocus\":17,\"fit\":\"cover\",\"width\":20,\"height\":13}","val":{"src":"data:image/webp;base64,UklGRkIAAABXRUJQVlA4IDYAAABQAwCdASoUAA0APtFUo0uoJKMhsAgBABoJZQAAW/ChohP7AAD+9hCVHb3Yjdh6HY9rWlHAAAA=","width":20,"height":13,"aspectRatio":1.5384615384615385,"originalName":"blob.png"}}